Metadata-Version: 2.0
Name: odoo9-addon-stock-disable-force-availability-button
Version: 9.0.1.0.0
Summary: Disable force availability button
Home-page: http://www.odoomrp.com
Author: OdooMRP team,AvanzOSC,Tecnativa - Pedro M. Baeza,Odoo Community Association (OCA),Agile Business Group
Author-email: support@odoo-community.org
License: AGPL-3
Platform: UNKNOWN
Requires-Dist: odoo (<9.1a,>=9.0a)
Classifier: Programming Language :: Python :: 2.7
Classifier: Framework :: Odoo
Classifier: License :: OSI Approved :: GNU Affero General Public License v3
